{
    "categories": [
        {
            "category": "Eat Out",
            "budget": 25
        },
        {
            "category": "Rent",
            "budget": 375
        },
        {
            "category": "Grocery",
            "budget": 110
        },
        {
            "category": "electricity",
            "budget": 150
        },
        {
            "category": "play",
            "budget": 130
        },
        {
            "category": "water",
            "budget": 200
        },
        {
            "category": "clothes",
            "budget": 250
        }
    ]
}
